README.md
setup.cfg
setup.py
rxmarbles/__init__.py
rxmarbles/__main__.py
rxmarbles/generator.py
rxmarbles/svgshapes.py
rxmarbles.egg-info/PKG-INFO
rxmarbles.egg-info/SOURCES.txt
rxmarbles.egg-info/dependency_links.txt
rxmarbles.egg-info/entry_points.txt
rxmarbles.egg-info/not-zip-safe
rxmarbles.egg-info/requires.txt
rxmarbles.egg-info/top_level.txt
rxmarbles/theme/__init__.py
rxmarbles/theme/default.py
rxmarbles/theme/pencil.py