Metadata-Version: 1.0
Name: rxmarbles
Version: 0.2.5
Summary: Marbles diagram generator
Home-page: https://bitbucket.org/achary/rx-marbles/
Author: Adam Charytoniuk
Author-email: adam.charytoniuk@gmail.com
License: MIT
Keywords: marbles,rx,diagrams,reactive
Platform: UNKNOWN
